Metadata-Version: 1.0
Name: sclimateday
Version: 2.0.0
Summary: ['Weather  forecast data']
Home-page: https://example.com
Author: Alex Enriquez Romero
Author-email: enriquezaer@gmail.com
License: MIT
Keywords: weather,forecast,openweather
Platform: UNKNOWN
